{"nodes": [{"id": "launchview", "label": "LaunchView.tsx", "file_type": "code", "source_file": "open-seo-main/src/client/features/audit/launch/LaunchView.tsx", "source_location": "L1"}, {"id": "launchview_launchview", "label": "LaunchView()", "file_type": "code", "source_file": "open-seo-main/src/client/features/audit/launch/LaunchView.tsx", "source_location": "L5"}], "edges": [{"source": "launchview", "target": "audithistorysection", "relation": "imports_from", "confidence": "EXTRACTED", "source_file": "open-seo-main/src/client/features/audit/launch/LaunchView.tsx", "source_location": "L1", "weight": 1.0}, {"source": "launchview", "target": "launchformcard", "relation": "imports_from", "confidence": "EXTRACTED", "source_file": "open-seo-main/src/client/features/audit/launch/LaunchView.tsx", "source_location": "L2", "weight": 1.0}, {"source": "launchview", "target": "uselaunchcontroller", "relation": "imports_from", "confidence": "EXTRACTED", "source_file": "open-seo-main/src/client/features/audit/launch/LaunchView.tsx", "source_location": "L3", "weight": 1.0}, {"source": "launchview", "target": "launchview_launchview", "relation": "contains", "confidence": "EXTRACTED", "source_file": "open-seo-main/src/client/features/audit/launch/LaunchView.tsx", "source_location": "L5", "weight": 1.0}]}