{"nodes": [{"id": "client_oauth", "label": "client_oauth.py", "file_type": "code", "source_file": "AI-Writer/backend/api/client_oauth.py", "source_location": "L1"}, {"id": "client_oauth_invitecreate", "label": "InviteCreate", "file_type": "code", "source_file": "AI-Writer/backend/api/client_oauth.py", "source_location": "L42"}, {"id": "basemodel", "label": "BaseModel", "file_type": "code", "source_file": "", "source_location": ""}, {"id": "client_oauth_inviteresponse", "label": "InviteResponse", "file_type": "code", "source_file": "AI-Writer/backend/api/client_oauth.py", "source_location": "L50"}, {"id": "client_oauth_propertyresponse", "label": "PropertyResponse", "file_type": "code", "source_file": "AI-Writer/backend/api/client_oauth.py", "source_location": "L58"}, {"id": "client_oauth_connectionresponse", "label": "ConnectionResponse", "file_type": "code", "source_file": "AI-Writer/backend/api/client_oauth.py", "source_location": "L65"}, {"id": "client_oauth_config", "label": "Config", "file_type": "code", "source_file": "AI-Writer/backend/api/client_oauth.py", "source_location": "L82"}, {"id": "client_oauth_invitevalidationresponse", "label": "InviteValidationResponse", "file_type": "code", "source_file": "AI-Writer/backend/api/client_oauth.py", "source_location": "L86"}, {"id": "client_oauth_get_active_client_or_404", "label": "_get_active_client_or_404()", "file_type": "code", "source_file": "AI-Writer/backend/api/client_oauth.py", "source_location": "L100"}, {"id": "client_oauth_check_invite_rate_limit", "label": "_check_invite_rate_limit()", "file_type": "code", "source_file": "AI-Writer/backend/api/client_oauth.py", "source_location": "L122"}, {"id": "client_oauth_create_invite", "label": "create_invite()", "file_type": "code", "source_file": "AI-Writer/backend/api/client_oauth.py", "source_location": "L161"}, {"id": "client_oauth_validate_invite", "label": "validate_invite()", "file_type": "code", "source_file": "AI-Writer/backend/api/client_oauth.py", "source_location": "L196"}, {"id": "client_oauth_list_connections", "label": "list_connections()", "file_type": "code", "source_file": "AI-Writer/backend/api/client_oauth.py", "source_location": "L231"}, {"id": "client_oauth_revoke_connection", "label": "revoke_connection()", "file_type": "code", "source_file": "AI-Writer/backend/api/client_oauth.py", "source_location": "L268"}, {"id": "client_oauth_start_google_oauth", "label": "start_google_oauth()", "file_type": "code", "source_file": "AI-Writer/backend/api/client_oauth.py", "source_location": "L309"}, {"id": "client_oauth_google_oauth_callback", "label": "google_oauth_callback()", "file_type": "code", "source_file": "AI-Writer/backend/api/client_oauth.py", "source_location": "L370"}, {"id": "client_oauth_rationale_1", "label": "REST API router for per-client OAuth credentials.  Endpoints:   POST   /api/clie", "file_type": "rationale", "source_file": "AI-Writer/backend/api/client_oauth.py", "source_location": "L1"}, {"id": "client_oauth_rationale_43", "label": "Request body for creating a magic link invite.", "file_type": "rationale", "source_file": "AI-Writer/backend/api/client_oauth.py", "source_location": "L43"}, {"id": "client_oauth_rationale_51", "label": "Response when creating a new magic link invite.", "file_type": "rationale", "source_file": "AI-Writer/backend/api/client_oauth.py", "source_location": "L51"}, {"id": "client_oauth_rationale_59", "label": "Key-value property associated with an OAuth connection.", "file_type": "rationale", "source_file": "AI-Writer/backend/api/client_oauth.py", "source_location": "L59"}, {"id": "client_oauth_rationale_66", "label": "OAuth connection response schema.      SECURITY: access_token and refresh_token", "file_type": "rationale", "source_file": "AI-Writer/backend/api/client_oauth.py", "source_location": "L66"}, {"id": "client_oauth_rationale_87", "label": "Response when validating a magic link invite token.", "file_type": "rationale", "source_file": "AI-Writer/backend/api/client_oauth.py", "source_location": "L87"}, {"id": "client_oauth_rationale_101", "label": "Return the Client row or raise 404.      Returns 404 for both missing AND archiv", "file_type": "rationale", "source_file": "AI-Writer/backend/api/client_oauth.py", "source_location": "L101"}, {"id": "client_oauth_rationale_123", "label": "Check if the client has exceeded the invite creation rate limit.      Raises 429", "file_type": "rationale", "source_file": "AI-Writer/backend/api/client_oauth.py", "source_location": "L123"}, {"id": "client_oauth_rationale_167", "label": "Create a magic link invite for client self-authorization.      The invite token", "file_type": "rationale", "source_file": "AI-Writer/backend/api/client_oauth.py", "source_location": "L167"}, {"id": "client_oauth_rationale_201", "label": "Validate a magic link invite token (PUBLIC endpoint).      Returns client name a", "file_type": "rationale", "source_file": "AI-Writer/backend/api/client_oauth.py", "source_location": "L201"}, {"id": "client_oauth_rationale_236", "label": "List all active OAuth connections for a client.      SECURITY: Encrypted tokens", "file_type": "rationale", "source_file": "AI-Writer/backend/api/client_oauth.py", "source_location": "L236"}, {"id": "client_oauth_rationale_274", "label": "Revoke (disconnect) an OAuth connection.      This soft-deletes the connection (", "file_type": "rationale", "source_file": "AI-Writer/backend/api/client_oauth.py", "source_location": "L274"}, {"id": "client_oauth_rationale_317", "label": "Start Google OAuth flow.      Supports two flows:     1. Direct flow: Agency sta", "file_type": "rationale", "source_file": "AI-Writer/backend/api/client_oauth.py", "source_location": "L317"}, {"id": "client_oauth_rationale_376", "label": "Handle Google OAuth callback (PUBLIC endpoint).      SECURITY: The state paramet", "file_type": "rationale", "source_file": "AI-Writer/backend/api/client_oauth.py", "source_location": "L376"}, {"id": "client_oauth_rationale_199", "label": "# NOTE: No get_current_user - this is a PUBLIC endpoint for /connect/[token] pag", "file_type": "rationale", "source_file": "AI-Writer/backend/api/client_oauth.py", "source_location": "L199"}], "edges": [{"source": "client_oauth", "target": "uuid", "relation": "imports", "confidence": "EXTRACTED", "source_file": "AI-Writer/backend/api/client_oauth.py", "source_location": "L18", "weight": 1.0}, {"source": "client_oauth", "target": "datetime", "relation": "imports_from", "confidence": "EXTRACTED", "source_file": "AI-Writer/backend/api/client_oauth.py", "source_location": "L19", "weight": 1.0}, {"source": "client_oauth", "target": "typing", "relation": "imports_from", "confidence": "EXTRACTED", "source_file": "AI-Writer/backend/api/client_oauth.py", "source_location": "L20", "weight": 1.0}, {"source": "client_oauth", "target": "fastapi", "relation": "imports_from", "confidence": "EXTRACTED", "source_file": "AI-Writer/backend/api/client_oauth.py", "source_location": "L22", "weight": 1.0}, {"source": "client_oauth", "target": "fastapi_responses", "relation": "imports_from", "confidence": "EXTRACTED", "source_file": "AI-Writer/backend/api/client_oauth.py", "source_location": "L23", "weight": 1.0}, {"source": "client_oauth", "target": "loguru", "relation": "imports_from", "confidence": "EXTRACTED", "source_file": "AI-Writer/backend/api/client_oauth.py", "source_location": "L24", "weight": 1.0}, {"source": "client_oauth", "target": "pydantic", "relation": "imports_from", "confidence": "EXTRACTED", "source_file": "AI-Writer/backend/api/client_oauth.py", "source_location": "L25", "weight": 1.0}, {"source": "client_oauth", "target": "sqlalchemy_orm", "relation": "imports_from", "confidence": "EXTRACTED", "source_file": "AI-Writer/backend/api/client_oauth.py", "source_location": "L26", "weight": 1.0}, {"source": "client_oauth", "target": "middleware_auth_middleware", "relation": "imports_from", "confidence": "EXTRACTED", "source_file": "AI-Writer/backend/api/client_oauth.py", "source_location": "L28", "weight": 1.0}, {"source": "client_oauth", "target": "models_client", "relation": "imports_from", "confidence": "EXTRACTED", "source_file": "AI-Writer/backend/api/client_oauth.py", "source_location": "L29", "weight": 1.0}, {"source": "client_oauth", "target": "models_client_oauth", "relation": "imports_from", "confidence": "EXTRACTED", "source_file": "AI-Writer/backend/api/client_oauth.py", "source_location": "L30", "weight": 1.0}, {"source": "client_oauth", "target": "services_client_oauth_service", "relation": "imports_from", "confidence": "EXTRACTED", "source_file": "AI-Writer/backend/api/client_oauth.py", "source_location": "L31", "weight": 1.0}, {"source": "client_oauth", "target": "services_shared_db", "relation": "imports_from", "confidence": "EXTRACTED", "source_file": "AI-Writer/backend/api/client_oauth.py", "source_location": "L32", "weight": 1.0}, {"source": "client_oauth", "target": "client_oauth_invitecreate", "relation": "contains", "confidence": "EXTRACTED", "source_file": "AI-Writer/backend/api/client_oauth.py", "source_location": "L42", "weight": 1.0}, {"source": "client_oauth_invitecreate", "target": "basemodel", "relation": "inherits", "confidence": "EXTRACTED", "source_file": "AI-Writer/backend/api/client_oauth.py", "source_location": "L42", "weight": 1.0}, {"source": "client_oauth", "target": "client_oauth_inviteresponse", "relation": "contains", "confidence": "EXTRACTED", "source_file": "AI-Writer/backend/api/client_oauth.py", "source_location": "L50", "weight": 1.0}, {"source": "client_oauth_inviteresponse", "target": "basemodel", "relation": "inherits", "confidence": "EXTRACTED", "source_file": "AI-Writer/backend/api/client_oauth.py", "source_location": "L50", "weight": 1.0}, {"source": "client_oauth", "target": "client_oauth_propertyresponse", "relation": "contains", "confidence": "EXTRACTED", "source_file": "AI-Writer/backend/api/client_oauth.py", "source_location": "L58", "weight": 1.0}, {"source": "client_oauth_propertyresponse", "target": "basemodel", "relation": "inherits", "confidence": "EXTRACTED", "source_file": "AI-Writer/backend/api/client_oauth.py", "source_location": "L58", "weight": 1.0}, {"source": "client_oauth", "target": "client_oauth_connectionresponse", "relation": "contains", "confidence": "EXTRACTED", "source_file": "AI-Writer/backend/api/client_oauth.py", "source_location": "L65", "weight": 1.0}, {"source": "client_oauth_connectionresponse", "target": "basemodel", "relation": "inherits", "confidence": "EXTRACTED", "source_file": "AI-Writer/backend/api/client_oauth.py", "source_location": "L65", "weight": 1.0}, {"source": "client_oauth", "target": "client_oauth_config", "relation": "contains", "confidence": "EXTRACTED", "source_file": "AI-Writer/backend/api/client_oauth.py", "source_location": "L82", "weight": 1.0}, {"source": "client_oauth", "target": "client_oauth_invitevalidationresponse", "relation": "contains", "confidence": "EXTRACTED", "source_file": "AI-Writer/backend/api/client_oauth.py", "source_location": "L86", "weight": 1.0}, {"source": "client_oauth_invitevalidationresponse", "target": "basemodel", "relation": "inherits", "confidence": "EXTRACTED", "source_file": "AI-Writer/backend/api/client_oauth.py", "source_location": "L86", "weight": 1.0}, {"source": "client_oauth", "target": "client_oauth_get_active_client_or_404", "relation": "contains", "confidence": "EXTRACTED", "source_file": "AI-Writer/backend/api/client_oauth.py", "source_location": "L100", "weight": 1.0}, {"source": "client_oauth", "target": "client_oauth_check_invite_rate_limit", "relation": "contains", "confidence": "EXTRACTED", "source_file": "AI-Writer/backend/api/client_oauth.py", "source_location": "L122", "weight": 1.0}, {"source": "client_oauth", "target": "client_oauth_create_invite", "relation": "contains", "confidence": "EXTRACTED", "source_file": "AI-Writer/backend/api/client_oauth.py", "source_location": "L161", "weight": 1.0}, {"source": "client_oauth", "target": "client_oauth_validate_invite", "relation": "contains", "confidence": "EXTRACTED", "source_file": "AI-Writer/backend/api/client_oauth.py", "source_location": "L196", "weight": 1.0}, {"source": "client_oauth", "target": "client_oauth_list_connections", "relation": "contains", "confidence": "EXTRACTED", "source_file": "AI-Writer/backend/api/client_oauth.py", "source_location": "L231", "weight": 1.0}, {"source": "client_oauth", "target": "client_oauth_revoke_connection", "relation": "contains", "confidence": "EXTRACTED", "source_file": "AI-Writer/backend/api/client_oauth.py", "source_location": "L268", "weight": 1.0}, {"source": "client_oauth", "target": "client_oauth_start_google_oauth", "relation": "contains", "confidence": "EXTRACTED", "source_file": "AI-Writer/backend/api/client_oauth.py", "source_location": "L309", "weight": 1.0}, {"source": "client_oauth", "target": "client_oauth_google_oauth_callback", "relation": "contains", "confidence": "EXTRACTED", "source_file": "AI-Writer/backend/api/client_oauth.py", "source_location": "L370", "weight": 1.0}, {"source": "client_oauth_create_invite", "target": "client_oauth_get_active_client_or_404", "relation": "calls", "confidence": "EXTRACTED", "source_file": "AI-Writer/backend/api/client_oauth.py", "source_location": "L175", "weight": 1.0}, {"source": "client_oauth_create_invite", "target": "client_oauth_check_invite_rate_limit", "relation": "calls", "confidence": "EXTRACTED", "source_file": "AI-Writer/backend/api/client_oauth.py", "source_location": "L178", "weight": 1.0}, {"source": "client_oauth_create_invite", "target": "client_oauth_inviteresponse", "relation": "calls", "confidence": "EXTRACTED", "source_file": "AI-Writer/backend/api/client_oauth.py", "source_location": "L188", "weight": 1.0}, {"source": "client_oauth_validate_invite", "target": "client_oauth_invitevalidationresponse", "relation": "calls", "confidence": "EXTRACTED", "source_file": "AI-Writer/backend/api/client_oauth.py", "source_location": "L217", "weight": 1.0}, {"source": "client_oauth_list_connections", "target": "client_oauth_get_active_client_or_404", "relation": "calls", "confidence": "EXTRACTED", "source_file": "AI-Writer/backend/api/client_oauth.py", "source_location": "L241", "weight": 1.0}, {"source": "client_oauth_list_connections", "target": "client_oauth_connectionresponse", "relation": "calls", "confidence": "EXTRACTED", "source_file": "AI-Writer/backend/api/client_oauth.py", "source_location": "L247", "weight": 1.0}, {"source": "client_oauth_list_connections", "target": "client_oauth_propertyresponse", "relation": "calls", "confidence": "EXTRACTED", "source_file": "AI-Writer/backend/api/client_oauth.py", "source_location": "L256", "weight": 1.0}, {"source": "client_oauth_revoke_connection", "target": "client_oauth_get_active_client_or_404", "relation": "calls", "confidence": "EXTRACTED", "source_file": "AI-Writer/backend/api/client_oauth.py", "source_location": "L279", "weight": 1.0}, {"source": "client_oauth_start_google_oauth", "target": "client_oauth_validate_invite", "relation": "calls", "confidence": "EXTRACTED", "source_file": "AI-Writer/backend/api/client_oauth.py", "source_location": "L333", "weight": 1.0}, {"source": "client_oauth_start_google_oauth", "target": "client_oauth_get_active_client_or_404", "relation": "calls", "confidence": "EXTRACTED", "source_file": "AI-Writer/backend/api/client_oauth.py", "source_location": "L352", "weight": 1.0}, {"source": "client_oauth_rationale_1", "target": "client_oauth", "relation": "rationale_for", "confidence": "EXTRACTED", "source_file": "AI-Writer/backend/api/client_oauth.py", "source_location": "L1", "weight": 1.0}, {"source": "client_oauth_rationale_43", "target": "client_oauth_invitecreate", "relation": "rationale_for", "confidence": "EXTRACTED", "source_file": "AI-Writer/backend/api/client_oauth.py", "source_location": "L43", "weight": 1.0}, {"source": "client_oauth_rationale_51", "target": "client_oauth_inviteresponse", "relation": "rationale_for", "confidence": "EXTRACTED", "source_file": "AI-Writer/backend/api/client_oauth.py", "source_location": "L51", "weight": 1.0}, {"source": "client_oauth_rationale_59", "target": "client_oauth_propertyresponse", "relation": "rationale_for", "confidence": "EXTRACTED", "source_file": "AI-Writer/backend/api/client_oauth.py", "source_location": "L59", "weight": 1.0}, {"source": "client_oauth_rationale_66", "target": "client_oauth_connectionresponse", "relation": "rationale_for", "confidence": "EXTRACTED", "source_file": "AI-Writer/backend/api/client_oauth.py", "source_location": "L66", "weight": 1.0}, {"source": "client_oauth_rationale_87", "target": "client_oauth_invitevalidationresponse", "relation": "rationale_for", "confidence": "EXTRACTED", "source_file": "AI-Writer/backend/api/client_oauth.py", "source_location": "L87", "weight": 1.0}, {"source": "client_oauth_rationale_101", "target": "client_oauth_get_active_client_or_404", "relation": "rationale_for", "confidence": "EXTRACTED", "source_file": "AI-Writer/backend/api/client_oauth.py", "source_location": "L101", "weight": 1.0}, {"source": "client_oauth_rationale_123", "target": "client_oauth_check_invite_rate_limit", "relation": "rationale_for", "confidence": "EXTRACTED", "source_file": "AI-Writer/backend/api/client_oauth.py", "source_location": "L123", "weight": 1.0}, {"source": "client_oauth_rationale_167", "target": "client_oauth_create_invite", "relation": "rationale_for", "confidence": "EXTRACTED", "source_file": "AI-Writer/backend/api/client_oauth.py", "source_location": "L167", "weight": 1.0}, {"source": "client_oauth_rationale_201", "target": "client_oauth_validate_invite", "relation": "rationale_for", "confidence": "EXTRACTED", "source_file": "AI-Writer/backend/api/client_oauth.py", "source_location": "L201", "weight": 1.0}, {"source": "client_oauth_rationale_236", "target": "client_oauth_list_connections", "relation": "rationale_for", "confidence": "EXTRACTED", "source_file": "AI-Writer/backend/api/client_oauth.py", "source_location": "L236", "weight": 1.0}, {"source": "client_oauth_rationale_274", "target": "client_oauth_revoke_connection", "relation": "rationale_for", "confidence": "EXTRACTED", "source_file": "AI-Writer/backend/api/client_oauth.py", "source_location": "L274", "weight": 1.0}, {"source": "client_oauth_rationale_317", "target": "client_oauth_start_google_oauth", "relation": "rationale_for", "confidence": "EXTRACTED", "source_file": "AI-Writer/backend/api/client_oauth.py", "source_location": "L317", "weight": 1.0}, {"source": "client_oauth_rationale_376", "target": "client_oauth_google_oauth_callback", "relation": "rationale_for", "confidence": "EXTRACTED", "source_file": "AI-Writer/backend/api/client_oauth.py", "source_location": "L376", "weight": 1.0}, {"source": "client_oauth_rationale_199", "target": "client_oauth", "relation": "rationale_for", "confidence": "EXTRACTED", "source_file": "AI-Writer/backend/api/client_oauth.py", "source_location": "L199", "weight": 1.0}]}