{"nodes": [{"id": "gsc", "label": "gsc.ts", "file_type": "code", "source_file": "AI-Writer/frontend/src/api/gsc.ts", "source_location": "L1"}, {"id": "gsc_gscapi", "label": "GSCAPI", "file_type": "code", "source_file": "AI-Writer/frontend/src/api/gsc.ts", "source_location": "L46"}, {"id": "gsc_gscapi_setauthtokengetter", "label": ".setAuthTokenGetter()", "file_type": "code", "source_file": "AI-Writer/frontend/src/api/gsc.ts", "source_location": "L53"}, {"id": "gsc_gscapi_getauthenticatedclient", "label": ".getAuthenticatedClient()", "file_type": "code", "source_file": "AI-Writer/frontend/src/api/gsc.ts", "source_location": "L60"}, {"id": "gsc_gscapi_getauthurl", "label": ".getAuthUrl()", "file_type": "code", "source_file": "AI-Writer/frontend/src/api/gsc.ts", "source_location": "L77"}, {"id": "gsc_gscapi_handlecallback", "label": ".handleCallback()", "file_type": "code", "source_file": "AI-Writer/frontend/src/api/gsc.ts", "source_location": "L91"}, {"id": "gsc_gscapi_getsites", "label": ".getSites()", "file_type": "code", "source_file": "AI-Writer/frontend/src/api/gsc.ts", "source_location": "L107"}, {"id": "gsc_gscapi_getanalytics", "label": ".getAnalytics()", "file_type": "code", "source_file": "AI-Writer/frontend/src/api/gsc.ts", "source_location": "L121"}, {"id": "gsc_gscapi_getsitemaps", "label": ".getSitemaps()", "file_type": "code", "source_file": "AI-Writer/frontend/src/api/gsc.ts", "source_location": "L135"}, {"id": "gsc_gscapi_getstatus", "label": ".getStatus()", "file_type": "code", "source_file": "AI-Writer/frontend/src/api/gsc.ts", "source_location": "L149"}, {"id": "gsc_gscapi_clearincomplete", "label": ".clearIncomplete()", "file_type": "code", "source_file": "AI-Writer/frontend/src/api/gsc.ts", "source_location": "L163"}, {"id": "gsc_gscapi_disconnect", "label": ".disconnect()", "file_type": "code", "source_file": "AI-Writer/frontend/src/api/gsc.ts", "source_location": "L177"}, {"id": "gsc_gscapi_healthcheck", "label": ".healthCheck()", "file_type": "code", "source_file": "AI-Writer/frontend/src/api/gsc.ts", "source_location": "L191"}], "edges": [{"source": "gsc", "target": "client", "relation": "imports_from", "confidence": "EXTRACTED", "source_file": "AI-Writer/frontend/src/api/gsc.ts", "source_location": "L3", "weight": 1.0}, {"source": "gsc", "target": "gsc_gscapi", "relation": "contains", "confidence": "EXTRACTED", "source_file": "AI-Writer/frontend/src/api/gsc.ts", "source_location": "L46", "weight": 1.0}, {"source": "gsc_gscapi", "target": "gsc_gscapi_setauthtokengetter", "relation": "method", "confidence": "EXTRACTED", "source_file": "AI-Writer/frontend/src/api/gsc.ts", "source_location": "L53", "weight": 1.0}, {"source": "gsc_gscapi", "target": "gsc_gscapi_getauthenticatedclient", "relation": "method", "confidence": "EXTRACTED", "source_file": "AI-Writer/frontend/src/api/gsc.ts", "source_location": "L60", "weight": 1.0}, {"source": "gsc_gscapi", "target": "gsc_gscapi_getauthurl", "relation": "method", "confidence": "EXTRACTED", "source_file": "AI-Writer/frontend/src/api/gsc.ts", "source_location": "L77", "weight": 1.0}, {"source": "gsc_gscapi", "target": "gsc_gscapi_handlecallback", "relation": "method", "confidence": "EXTRACTED", "source_file": "AI-Writer/frontend/src/api/gsc.ts", "source_location": "L91", "weight": 1.0}, {"source": "gsc_gscapi", "target": "gsc_gscapi_getsites", "relation": "method", "confidence": "EXTRACTED", "source_file": "AI-Writer/frontend/src/api/gsc.ts", "source_location": "L107", "weight": 1.0}, {"source": "gsc_gscapi", "target": "gsc_gscapi_getanalytics", "relation": "method", "confidence": "EXTRACTED", "source_file": "AI-Writer/frontend/src/api/gsc.ts", "source_location": "L121", "weight": 1.0}, {"source": "gsc_gscapi", "target": "gsc_gscapi_getsitemaps", "relation": "method", "confidence": "EXTRACTED", "source_file": "AI-Writer/frontend/src/api/gsc.ts", "source_location": "L135", "weight": 1.0}, {"source": "gsc_gscapi", "target": "gsc_gscapi_getstatus", "relation": "method", "confidence": "EXTRACTED", "source_file": "AI-Writer/frontend/src/api/gsc.ts", "source_location": "L149", "weight": 1.0}, {"source": "gsc_gscapi", "target": "gsc_gscapi_clearincomplete", "relation": "method", "confidence": "EXTRACTED", "source_file": "AI-Writer/frontend/src/api/gsc.ts", "source_location": "L163", "weight": 1.0}, {"source": "gsc_gscapi", "target": "gsc_gscapi_disconnect", "relation": "method", "confidence": "EXTRACTED", "source_file": "AI-Writer/frontend/src/api/gsc.ts", "source_location": "L177", "weight": 1.0}, {"source": "gsc_gscapi", "target": "gsc_gscapi_healthcheck", "relation": "method", "confidence": "EXTRACTED", "source_file": "AI-Writer/frontend/src/api/gsc.ts", "source_location": "L191", "weight": 1.0}, {"source": "gsc_gscapi_getauthurl", "target": "gsc_gscapi_getauthenticatedclient", "relation": "calls", "confidence": "EXTRACTED", "source_file": "AI-Writer/frontend/src/api/gsc.ts", "source_location": "L79", "weight": 1.0}, {"source": "gsc_gscapi_handlecallback", "target": "gsc_gscapi_getauthenticatedclient", "relation": "calls", "confidence": "EXTRACTED", "source_file": "AI-Writer/frontend/src/api/gsc.ts", "source_location": "L93", "weight": 1.0}, {"source": "gsc_gscapi_getsites", "target": "gsc_gscapi_getauthenticatedclient", "relation": "calls", "confidence": "EXTRACTED", "source_file": "AI-Writer/frontend/src/api/gsc.ts", "source_location": "L109", "weight": 1.0}, {"source": "gsc_gscapi_getanalytics", "target": "gsc_gscapi_getauthenticatedclient", "relation": "calls", "confidence": "EXTRACTED", "source_file": "AI-Writer/frontend/src/api/gsc.ts", "source_location": "L123", "weight": 1.0}, {"source": "gsc_gscapi_getsitemaps", "target": "gsc_gscapi_getauthenticatedclient", "relation": "calls", "confidence": "EXTRACTED", "source_file": "AI-Writer/frontend/src/api/gsc.ts", "source_location": "L137", "weight": 1.0}, {"source": "gsc_gscapi_getstatus", "target": "gsc_gscapi_getauthenticatedclient", "relation": "calls", "confidence": "EXTRACTED", "source_file": "AI-Writer/frontend/src/api/gsc.ts", "source_location": "L151", "weight": 1.0}, {"source": "gsc_gscapi_clearincomplete", "target": "gsc_gscapi_getauthenticatedclient", "relation": "calls", "confidence": "EXTRACTED", "source_file": "AI-Writer/frontend/src/api/gsc.ts", "source_location": "L165", "weight": 1.0}, {"source": "gsc_gscapi_disconnect", "target": "gsc_gscapi_getauthenticatedclient", "relation": "calls", "confidence": "EXTRACTED", "source_file": "AI-Writer/frontend/src/api/gsc.ts", "source_location": "L179", "weight": 1.0}]}