{"nodes": [{"id": "analytics_worker", "label": "analytics-worker.ts", "file_type": "code", "source_file": "open-seo-main/src/server/workers/analytics-worker.ts", "source_location": "L1"}, {"id": "analytics_worker_recordduration", "label": "recordDuration()", "file_type": "code", "source_file": "open-seo-main/src/server/workers/analytics-worker.ts", "source_location": "L53"}, {"id": "analytics_worker_getaverageduration", "label": "getAverageDuration()", "file_type": "code", "source_file": "open-seo-main/src/server/workers/analytics-worker.ts", "source_location": "L61"}, {"id": "analytics_worker_emitmetrics", "label": "emitMetrics()", "file_type": "code", "source_file": "open-seo-main/src/server/workers/analytics-worker.ts", "source_location": "L67"}, {"id": "analytics_worker_startanalyticsworker", "label": "startAnalyticsWorker()", "file_type": "code", "source_file": "open-seo-main/src/server/workers/analytics-worker.ts", "source_location": "L85"}, {"id": "analytics_worker_stopanalyticsworker", "label": "stopAnalyticsWorker()", "file_type": "code", "source_file": "open-seo-main/src/server/workers/analytics-worker.ts", "source_location": "L188"}], "edges": [{"source": "analytics_worker", "target": "bullmq", "relation": "imports_from", "confidence": "EXTRACTED", "source_file": "open-seo-main/src/server/workers/analytics-worker.ts", "source_location": "L14", "weight": 1.0}, {"source": "analytics_worker", "target": "node_url", "relation": "imports_from", "confidence": "EXTRACTED", "source_file": "open-seo-main/src/server/workers/analytics-worker.ts", "source_location": "L15", "weight": 1.0}, {"source": "analytics_worker", "target": "redis", "relation": "imports_from", "confidence": "EXTRACTED", "source_file": "open-seo-main/src/server/workers/analytics-worker.ts", "source_location": "L16", "weight": 1.0}, {"source": "analytics_worker", "target": "logger", "relation": "imports_from", "confidence": "EXTRACTED", "source_file": "open-seo-main/src/server/workers/analytics-worker.ts", "source_location": "L17", "weight": 1.0}, {"source": "analytics_worker", "target": "analyticsqueue", "relation": "imports_from", "confidence": "EXTRACTED", "source_file": "open-seo-main/src/server/workers/analytics-worker.ts", "source_location": "L18", "weight": 1.0}, {"source": "analytics_worker", "target": "analytics_worker_recordduration", "relation": "contains", "confidence": "EXTRACTED", "source_file": "open-seo-main/src/server/workers/analytics-worker.ts", "source_location": "L53", "weight": 1.0}, {"source": "analytics_worker", "target": "analytics_worker_getaverageduration", "relation": "contains", "confidence": "EXTRACTED", "source_file": "open-seo-main/src/server/workers/analytics-worker.ts", "source_location": "L61", "weight": 1.0}, {"source": "analytics_worker", "target": "analytics_worker_emitmetrics", "relation": "contains", "confidence": "EXTRACTED", "source_file": "open-seo-main/src/server/workers/analytics-worker.ts", "source_location": "L67", "weight": 1.0}, {"source": "analytics_worker", "target": "analytics_worker_startanalyticsworker", "relation": "contains", "confidence": "EXTRACTED", "source_file": "open-seo-main/src/server/workers/analytics-worker.ts", "source_location": "L85", "weight": 1.0}, {"source": "analytics_worker", "target": "analytics_worker_stopanalyticsworker", "relation": "contains", "confidence": "EXTRACTED", "source_file": "open-seo-main/src/server/workers/analytics-worker.ts", "source_location": "L188", "weight": 1.0}, {"source": "analytics_worker_emitmetrics", "target": "analytics_worker_getaverageduration", "relation": "calls", "confidence": "EXTRACTED", "source_file": "open-seo-main/src/server/workers/analytics-worker.ts", "source_location": "L68", "weight": 1.0}, {"source": "analytics_worker_stopanalyticsworker", "target": "analytics_worker_emitmetrics", "relation": "calls", "confidence": "EXTRACTED", "source_file": "open-seo-main/src/server/workers/analytics-worker.ts", "source_location": "L194", "weight": 1.0}]}