{"nodes": [{"id": "redis", "label": "redis.ts", "file_type": "code", "source_file": "open-seo-main/src/server/lib/redis.ts", "source_location": "L1"}, {"id": "redis_getredisurl", "label": "getRedisUrl()", "file_type": "code", "source_file": "open-seo-main/src/server/lib/redis.ts", "source_location": "L21"}, {"id": "redis_createredisconnection", "label": "createRedisConnection()", "file_type": "code", "source_file": "open-seo-main/src/server/lib/redis.ts", "source_location": "L50"}, {"id": "redis_getsharedbullmqconnection", "label": "getSharedBullMQConnection()", "file_type": "code", "source_file": "open-seo-main/src/server/lib/redis.ts", "source_location": "L67"}, {"id": "redis_closebullmqconnections", "label": "closeBullMQConnections()", "file_type": "code", "source_file": "open-seo-main/src/server/lib/redis.ts", "source_location": "L86"}, {"id": "redis_closeredis", "label": "closeRedis()", "file_type": "code", "source_file": "open-seo-main/src/server/lib/redis.ts", "source_location": "L106"}], "edges": [{"source": "redis", "target": "ioredis", "relation": "imports_from", "confidence": "EXTRACTED", "source_file": "open-seo-main/src/server/lib/redis.ts", "source_location": "L10", "weight": 1.0}, {"source": "redis", "target": "logger", "relation": "imports_from", "confidence": "EXTRACTED", "source_file": "open-seo-main/src/server/lib/redis.ts", "source_location": "L11", "weight": 1.0}, {"source": "redis", "target": "redis_getredisurl", "relation": "contains", "confidence": "EXTRACTED", "source_file": "open-seo-main/src/server/lib/redis.ts", "source_location": "L21", "weight": 1.0}, {"source": "redis", "target": "redis_createredisconnection", "relation": "contains", "confidence": "EXTRACTED", "source_file": "open-seo-main/src/server/lib/redis.ts", "source_location": "L50", "weight": 1.0}, {"source": "redis", "target": "redis_getsharedbullmqconnection", "relation": "contains", "confidence": "EXTRACTED", "source_file": "open-seo-main/src/server/lib/redis.ts", "source_location": "L67", "weight": 1.0}, {"source": "redis", "target": "redis_closebullmqconnections", "relation": "contains", "confidence": "EXTRACTED", "source_file": "open-seo-main/src/server/lib/redis.ts", "source_location": "L86", "weight": 1.0}, {"source": "redis", "target": "redis_closeredis", "relation": "contains", "confidence": "EXTRACTED", "source_file": "open-seo-main/src/server/lib/redis.ts", "source_location": "L106", "weight": 1.0}, {"source": "redis_createredisconnection", "target": "redis_getredisurl", "relation": "calls", "confidence": "EXTRACTED", "source_file": "open-seo-main/src/server/lib/redis.ts", "source_location": "L51", "weight": 1.0}, {"source": "redis_getsharedbullmqconnection", "target": "redis_getredisurl", "relation": "calls", "confidence": "EXTRACTED", "source_file": "open-seo-main/src/server/lib/redis.ts", "source_location": "L73", "weight": 1.0}]}