{"nodes": [{"id": "errorboundary", "label": "ErrorBoundary.tsx", "file_type": "code", "source_file": "AI-Writer/frontend/src/components/shared/ErrorBoundary.tsx", "source_location": "L1"}, {"id": "errorboundary_constructor", "label": "constructor()", "file_type": "code", "source_file": "AI-Writer/frontend/src/components/shared/ErrorBoundary.tsx", "source_location": "L31"}, {"id": "errorboundary_getderivedstatefromerror", "label": "getDerivedStateFromError()", "file_type": "code", "source_file": "AI-Writer/frontend/src/components/shared/ErrorBoundary.tsx", "source_location": "L41"}, {"id": "errorboundary_componentdidcatch", "label": "componentDidCatch()", "file_type": "code", "source_file": "AI-Writer/frontend/src/components/shared/ErrorBoundary.tsx", "source_location": "L45"}, {"id": "errorboundary_logerrortoservice", "label": "logErrorToService()", "file_type": "code", "source_file": "AI-Writer/frontend/src/components/shared/ErrorBoundary.tsx", "source_location": "L54"}], "edges": [{"source": "errorboundary", "target": "react", "relation": "imports_from", "confidence": "EXTRACTED", "source_file": "AI-Writer/frontend/src/components/shared/ErrorBoundary.tsx", "source_location": "L1", "weight": 1.0}, {"source": "errorboundary", "target": "lucide_react", "relation": "imports_from", "confidence": "EXTRACTED", "source_file": "AI-Writer/frontend/src/components/shared/ErrorBoundary.tsx", "source_location": "L2", "weight": 1.0}, {"source": "errorboundary", "target": "errorboundary_constructor", "relation": "contains", "confidence": "EXTRACTED", "source_file": "AI-Writer/frontend/src/components/shared/ErrorBoundary.tsx", "source_location": "L31", "weight": 1.0}, {"source": "errorboundary", "target": "errorboundary_getderivedstatefromerror", "relation": "contains", "confidence": "EXTRACTED", "source_file": "AI-Writer/frontend/src/components/shared/ErrorBoundary.tsx", "source_location": "L41", "weight": 1.0}, {"source": "errorboundary", "target": "errorboundary_componentdidcatch", "relation": "contains", "confidence": "EXTRACTED", "source_file": "AI-Writer/frontend/src/components/shared/ErrorBoundary.tsx", "source_location": "L45", "weight": 1.0}, {"source": "errorboundary", "target": "errorboundary_logerrortoservice", "relation": "contains", "confidence": "EXTRACTED", "source_file": "AI-Writer/frontend/src/components/shared/ErrorBoundary.tsx", "source_location": "L54", "weight": 1.0}, {"source": "errorboundary_componentdidcatch", "target": "errorboundary_logerrortoservice", "relation": "calls", "confidence": "EXTRACTED", "source_file": "AI-Writer/frontend/src/components/shared/ErrorBoundary.tsx", "source_location": "L51", "weight": 1.0}]}